{
    "thread": {
        "uuid": "8b05082f5e44d133fd684737fc09a77dc07af553",
        "url": "https://www.bhaskar.com/local/rajasthan/jaipur/news/rajasthan-is-number-one-so-far-in-the-national-nutrition-fortnight-134897714.html",
        "site_full": "www.bhaskar.com",
        "site": "bhaskar.com",
        "site_section": "http://www.bhaskar.com/rss-feed/1740",
        "site_categories": [
            "tech",
            "email",
            "top_news_in",
            "top_news_kw",
            "top_news_ae",
            "top_news"
        ],
        "section_title": "राजस्थान | दैनिक भास्कर",
        "site_title": "Hindi News; Latest Hindi News, Breaking Hindi News Live, Hindi Samachar (हिंदी समाचार), Hindi News Paper Today - Dainik Bhaskar",
        "title": "राष्ट्रीय पोषण पखवाड़ा में अभी तक नंबर वन है राजस्थान",
        "title_full": "राष्ट्रीय पोषण पखवाड़ा में अभी तक नंबर वन है राजस्थान",
        "published": "2025-04-24T02:03:00.000+03:00",
        "replies_count": 0,
        "participants_count": 1,
        "site_type": "news",
        "country": "IN",
        "main_image": "https://images.bhaskarassets.com/web2images/521/2020/11/db_1604320813.png",
        "performance_score": 0,
        "domain_rank": 18180,
        "domain_rank_updated": "2025-04-22T00:00:00.000+03:00",
        "licensing_agency": [],
        "social": {
            "facebook": {
                "likes": 0,
                "comments": 0,
                "shares": 0
            },
            "vk": {
                "shares": 0
            }
        }
    },
    "uuid": "8b05082f5e44d133fd684737fc09a77dc07af553",
    "url": "https://www.bhaskar.com/local/rajasthan/jaipur/news/rajasthan-is-number-one-so-far-in-the-national-nutrition-fortnight-134897714.html",
    "ord_in_thread": 0,
    "author": "@dainikbhaskar",
    "published": "2025-04-24T02:03:00.000+03:00",
    "title": "राष्ट्रीय पोषण पखवाड़ा में अभी तक नंबर वन है राजस्थान",
    "text": "Hindi NewsLocalRajasthanJaipur- Rajasthan Is Number One So Far In The National Nutrition Fortnight\nराष्ट्रीय पोषण पखवाड़ा में अभी तक नंबर वन है राजस्थान\n- कॉपी लिंक\nराष्ट्रीय पोषण पखवाड़ा-2025 के अंतिम दिन जयपुर जिला उपनिदेशक कार्यालय समेकित बाल विकास सेवाएं की ओर से जिला स्तरीय कार्यक्रम आयोजित किया गया। महिला बाल विकास शासन सचिव महेंद्र सोनी ने कार्यक्रम में कहा कि यह खुशी की बात है, जो राष्ट्रीय पोषण पखवाड़े मे\nपीपलू ने बढ़ाया राजस्थान का मान : उन्होंने बताया कि प्रधानमंत्री ने लोक सेवक दिवस पर आयोजित कार्यक्रम में राजस्थान के टोंक जिले के पीपलू ब्लॉक में पिछले दो वर्ष के मुकाबले इस वर्ष आंगनबाड़ी के बच्चों की मेजरमेंट एफिशिएंसी 20 प्रतिशत से बढ़कर 99 प्रतिशत होने का उल्लेख कर, प्रशंसा की है। प्रधानमंत्री के पीपलू का उल्लेख करना हमारे लिए गर्व का विषय है और प्रेरणादायी है।\nडेटा डालते हुए बरते सतर्कता : उन्होंने कहा कि डेटा डालते समय सतर्कता बरते। पुराने डेटा को रिपीट करने के स्थान पर नए सिरे से वास्तविक मेजरमेंट करके ही डेटा अपलोड किए जाने चाहिए। पोषण के आंकड़े वास्तविक हो इसके लिए नियमित प्रशिक्षण आवश्यक है। देश में सभी योजनाओं में राजस्थान नंबर वन पर बना रहें, इसके लिए हम सभी को पूर्ण क्षमता से कार्य करना होगा।\nनिदेशक समेकित बाल विकास सेवाएं ओपी बुनकर ने कहा कि बच्चों के पोषण के लिए प्रतिबद्धता से कार्य करना चाहिए। पिछले वर्ष पोषण माह में राजस्थान राष्ट्रीय स्तर पर चौथे स्थान पर रहा है। इस वर्ष अभी तक राजस्थान नंबर वन पर चल रहा है। हमें अंतिम रूप से नंबर वन पर बने रहने के लिए आखिरी दौर में और मेहनत से कार्य किया जाए ताकि हम राष्ट्रीय स्तर पर टॉप पर बने रहे।\nनिदेशक ने महिला पर्यवेक्षकों, सीडीपीओ, आंगनबाड़ी कार्यकर्ताओं को प्रेरित करते हुए कहा कि गर्भवती और धात्री महिलाओं को एनीमिया से बचाने के लिए और उनका सुपोषण सुनिश्चित करने के लिए अभियान के रूप में कार्य करें।\nइस अवसर पर जयपुर जिला उपनिदेशक कार्यालय समेकित बाल विकास सेवाएं के कार्मिकों को सम्मानित भी किया गया। वहीं धात्री माताओं का स्वागत किया गया।\nनजदीक स्कूल में होंगे रि-लोकेट आंगनबाड़ी केंद्र\nपूरी खबर पढ़ें ऐप परप्रीमियम मेंबरशिप है तो\nलॉगिन करें",
    "highlightText": "",
    "highlightTitle": "",
    "highlightThreadTitle": "",
    "language": "hindi",
    "sentiment": "positive",
    "categories": [
        "Health",
        "Social Issue",
        "Education"
    ],
    "topics": [
        "Health->diet",
        "Health->health organisation",
        "Social Issue->demographics",
        "Social Issue->population and census",
        "Education->students",
        "Education->educational grading"
    ],
    "ai_allow": true,
    "has_canonical": false,
    "breaking": true,
    "webz_reporter": false,
    "external_links": [],
    "entities": {
        "persons": [],
        "locations": [],
        "organizations": []
    },
    "syndication": {
        "syndicated": null,
        "syndicate_id": null,
        "first_syndicated": false
    },
    "trust": {
        "categories": [],
        "bias": null,
        "source": {
            "type": null,
            "city": null,
            "state": null,
            "country": null,
            "domain_type": null,
            "agency": null,
            "organization_name": null
        }
    },
    "rating": null,
    "crawled": "2025-04-24T02:20:07.212+03:00",
    "updated": "2025-04-24T02:20:07.212+03:00"
}