{
    "thread": {
        "uuid": "5e1e6073b3463d491a2b2b267644b16926d29d05",
        "url": "https://www.tupi.fm/entretenimento/skincare-matinal-essencial-para-evitar-rugas-e-manchas",
        "site_full": "www.tupi.fm",
        "site": "tupi.fm",
        "site_section": "https://www.tupi.fm",
        "site_categories": [
            "media"
        ],
        "section_title": "Super Rádio Tupi - Ouça e Assista AO VIVO",
        "site_title": "Super Rádio Tupi - Ouça e Assista AO VIVO",
        "title": "Skincare matinal essencial para evitar rugas e manchas",
        "title_full": "Skincare matinal essencial para evitar rugas e manchas",
        "published": "2025-04-24T01:06:00.000+03:00",
        "replies_count": 0,
        "participants_count": 1,
        "site_type": "news",
        "country": "BR",
        "main_image": "https://www.tupi.fm/wp-content/uploads/2025/04/skincare-_1745342508395.jpg",
        "performance_score": 0,
        "domain_rank": 63566,
        "domain_rank_updated": "2025-04-22T00:00:00.000+03:00",
        "licensing_agency": [],
        "social": {
            "facebook": {
                "likes": 0,
                "comments": 0,
                "shares": 0
            },
            "vk": {
                "shares": 0
            }
        }
    },
    "uuid": "5e1e6073b3463d491a2b2b267644b16926d29d05",
    "url": "https://www.tupi.fm/entretenimento/skincare-matinal-essencial-para-evitar-rugas-e-manchas",
    "ord_in_thread": 0,
    "author": "Mariana Paris",
    "published": "2025-04-24T01:06:00.000+03:00",
    "title": "Skincare matinal essencial para evitar rugas e manchas",
    "text": "Uma rotina de skincare matinal é essencial para manter a saúde e a aparência da pele. Ao acordar, a pele precisa de cuidados específicos para enfrentar as agressões do dia, como poluição e exposição solar. Além disso, a aplicação correta de produtos pode ajudar a prevenir o envelhecimento precoce e manter a pele hidratada e protegida.\nAdotar uma rotina de cuidados pela manhã pode parecer desafiador, mas é um investimento valioso para a saúde da pele. Com passos simples e produtos adequados, é possível criar um hábito que trará benefícios a longo prazo. A seguir, serão apresentados os passos essenciais para uma rotina de skincare matinal eficaz.\nQuais são os passos essenciais para a rotina de skincare matinal? Para garantir que a pele esteja bem cuidada e preparada para o dia, é importante seguir uma sequência de passos que envolvem limpeza, hidratação e proteção. Cada etapa tem sua importância e contribui para a saúde geral da pele.\nO primeiro passo é a limpeza, que remove impurezas acumuladas durante a noite. Em seguida, a aplicação de um tônico ajuda a equilibrar o pH da pele. A hidratação é crucial para manter a pele macia e evitar a desidratação. Por fim, a proteção solar é indispensável para prevenir danos causados pelos raios UV.\nPasso a Passo da Rotina de Skincare Matinal Limpeza: Utilize um limpador facial suave para remover oleosidade e impurezas. Escolha um produto adequado ao seu tipo de pele, seja ela oleosa, seca ou mista. Tônico: Aplique um tônico facial para equilibrar o pH da pele e prepará-la para os próximos passos. O tônico também ajuda a remover resíduos que o limpador pode ter deixado. Sérum: Opte por um sérum com ingredientes ativos que atendam às necessidades específicas da sua pele, como vitamina C para luminosidade ou ácido hialurônico para hidratação. Hidratante: Aplique um hidratante adequado ao seu tipo de pele. A hidratação é fundamental para manter a elasticidade e a saúde da pele. Protetor Solar: Finalize a rotina com um protetor solar de amplo espectro, com fator de proteção adequado. Este passo é crucial para proteger a pele dos danos solares e prevenir o envelhecimento precoce. Por que o protetor solar é indispensável na rotina matinal? O uso diário de protetor solar é um dos passos mais importantes na rotina de skincare matinal. A exposição aos raios UV pode causar danos significativos à pele, incluindo queimaduras, manchas e aumento do risco de câncer de pele. Além disso, os raios UV são responsáveis por acelerar o processo de envelhecimento, resultando em rugas e perda de firmeza.\nPortanto, aplicar protetor solar diariamente, mesmo em dias nublados ou quando se permanece em ambientes fechados, é essencial para manter a pele saudável e protegida. Escolher um produto com fator de proteção solar (FPS) adequado e reaplicá-lo ao longo do dia, se necessário, são práticas recomendadas para uma proteção eficaz.\nEstabelecer uma rotina de skincare matinal não precisa ser complicado. Com passos simples e produtos adequados, é possível cuidar da pele de forma eficaz e prática. A chave está na consistência e na escolha de produtos que atendam às necessidades específicas de cada tipo de pele.\nAlém disso, é importante lembrar que a rotina de skincare deve ser adaptada conforme as mudanças nas condições da pele e nas estações do ano. Consultar um dermatologista pode ser útil para personalizar a rotina e garantir que a pele receba os cuidados necessários para se manter saudável e radiante.",
    "highlightText": "",
    "highlightTitle": "",
    "highlightThreadTitle": "",
    "language": "portuguese",
    "sentiment": "positive",
    "categories": [
        "Health",
        "Lifestyle and Leisure",
        "Human Interest"
    ],
    "topics": [
        "Health->health treatment and procedure",
        "Lifestyle and Leisure->wellness",
        "Lifestyle and Leisure->lifestyle"
    ],
    "ai_allow": true,
    "has_canonical": false,
    "breaking": false,
    "webz_reporter": false,
    "external_links": [
        "https://assets.pinterest.com/ext/embed.html?id=936889528711628875",
        "https://assets.pinterest.com/ext/embed.html?id=90986854971043559",
        "https://www.assets.pinterest.com/ext/embed.html?id=90986854971043559",
        "https://assets.pinterest.com/ext/embed.html",
        "https://www.assets.pinterest.com/ext/embed.html?id=936889528711628875"
    ],
    "entities": {
        "persons": [],
        "locations": [],
        "organizations": []
    },
    "syndication": {
        "syndicated": null,
        "syndicate_id": null,
        "first_syndicated": false
    },
    "trust": {
        "categories": [],
        "bias": null,
        "source": {
            "type": null,
            "city": null,
            "state": null,
            "country": null,
            "domain_type": null,
            "agency": null,
            "organization_name": null
        }
    },
    "rating": null,
    "crawled": "2025-04-24T01:17:22.306+03:00",
    "updated": "2025-04-24T01:17:22.306+03:00"
}