{
    "thread": {
        "uuid": "2c8a8d36fb9b83601deec675526a69d5b3181311",
        "url": "https://xxrb.jxnews.com.cn/system/2025/04/24/020851329.shtml",
        "site_full": "xxrb.jxnews.com.cn",
        "site": "jxnews.com.cn",
        "site_section": "http://xxrb.jxnews.com.cn",
        "site_categories": [],
        "section_title": "信息日报 江西政经读本",
        "site_title": null,
        "title": "江西举办孤独症主题观影活动-信息日报",
        "title_full": "江西举办孤独症主题观影活动-信息日报",
        "published": "2025-04-24T02:17:30.903+03:00",
        "replies_count": 0,
        "participants_count": 0,
        "site_type": "news",
        "country": "CN",
        "main_image": "",
        "performance_score": 0,
        "domain_rank": 20835,
        "domain_rank_updated": "2025-04-22T00:00:00.000+03:00",
        "licensing_agency": [],
        "social": {
            "facebook": {
                "likes": 0,
                "comments": 0,
                "shares": 0
            },
            "vk": {
                "shares": 0
            }
        }
    },
    "uuid": "2c8a8d36fb9b83601deec675526a69d5b3181311",
    "url": "https://xxrb.jxnews.com.cn/system/2025/04/24/020851329.shtml",
    "ord_in_thread": 0,
    "author": null,
    "published": "2025-04-24T02:17:30.903+03:00",
    "title": "江西举办孤独症主题观影活动-信息日报",
    "text": "您当前的位置 ： > >\n江西举办孤独症主题观影活动\n2025-04-24 06:53:29 来源：大江网-信息日报 编辑：王世强 作者：刘文琴 王琴红\n本报讯 刘文琴、信息日报全媒体记者王琴红报道：4月22日，在第18个“世界孤独症日”宣传月期间，江西省精神残疾人及亲友协会联合江西省残疾人联合会在南昌举办孤独症主题纪录片《特别的你》观影公益活动。\n观影活动现场(江西省精神残疾人及亲友协会供图)\n此次活动以“特别的你，特别的爱”为主题，旨在提高社会对孤独症群体的认知与理解，倡导包容友爱的社会环境。江西多所特殊教育学校、孤独症服务机构代表、孤独症家庭及爱心企业、社会人士代表等共150余人参加。\n活动现场，多位孤独症人士用葫芦丝演奏了《月光下的凤尾竹》，展现了他们的艺术潜能和积极向上的精神风貌。随后，全体观众共同观看了时长110分钟的纪录片《特别的你》。影片通过真实案例，生动呈现了孤独症群体的生活状态与家庭面临的挑战，以及社会各界的温情支持，引发观众深刻共鸣。\n据了解，孤独症谱系障碍(ASD)是一种发病于婴幼儿阶段的神经系统发育障碍。数据显示，我国孤独症患者数量已超1000万，且发病率逐年攀升。孤独症群体及其家庭在生活、教育、就业等方面面临诸多挑战，需要全社会共同关注和支持。\n信息日报新闻，未经授权不得转载\n相关阅读",
    "highlightText": "",
    "highlightTitle": "",
    "highlightThreadTitle": "",
    "language": "chinese",
    "sentiment": "positive",
    "categories": [
        "Health"
    ],
    "topics": [
        "Health->developmental disorder",
        "Health->health organisation"
    ],
    "ai_allow": true,
    "has_canonical": false,
    "breaking": false,
    "webz_reporter": false,
    "external_links": [],
    "entities": {
        "persons": [],
        "locations": [],
        "organizations": []
    },
    "syndication": {
        "syndicated": null,
        "syndicate_id": null,
        "first_syndicated": false
    },
    "trust": {
        "categories": [],
        "bias": null,
        "source": {
            "type": null,
            "city": null,
            "state": null,
            "country": null,
            "domain_type": null,
            "agency": null,
            "organization_name": null
        }
    },
    "rating": null,
    "crawled": "2025-04-24T02:17:30.903+03:00",
    "updated": "2025-04-24T02:17:30.903+03:00"
}